citizenk/__init__.py
citizenk/agent.py
citizenk/citizenk.py
citizenk/kafka_adapter.py
citizenk/murmur2.py
citizenk/tasks.py
citizenk/topic.py
citizenk/utils.py
citizenk-0.1.66.dist-info/METADATA
citizenk-0.1.66.dist-info/WHEEL
citizenk-0.1.66.dist-info/RECORD
